{"DocumentConnection":{"type":"DocumentConnection","resolveType":"multiCollectionDocumentList","collections":["home","page","post"]},"Node":{"type":"Node","resolveType":"nodeDocument"},"DocumentNode":{"type":"DocumentNode","resolveType":"multiCollectionDocument","createDocument":"create","updateDocument":"update"},"HomeBlocks":{"type":"HomeBlocks","resolveType":"unionData","typeMap":{"hero":"HomeBlocksHero","imageText50":"HomeBlocksImageText50","features":"HomeBlocksFeatures"}},"Home":{"type":"Home","resolveType":"collectionDocument","collection":"home","createHome":"create","updateHome":"update"},"HomeConnection":{"type":"HomeConnection","resolveType":"collectionDocumentList","collection":"home"},"Page":{"type":"Page","resolveType":"collectionDocument","collection":"page","createPage":"create","updatePage":"update"},"PageConnection":{"type":"PageConnection","resolveType":"collectionDocumentList","collection":"page"},"Post":{"type":"Post","resolveType":"collectionDocument","collection":"post","createPost":"create","updatePost":"update"},"PostConnection":{"type":"PostConnection","resolveType":"collectionDocumentList","collection":"post"}}